{
  "ID": "BASE",
  "Vision": {
    "range": 0
  },
  "Defense": {
    "defense": 3
  },
  "Capturable": {
    "points": 20
  },
  "Funds": {
    "amount": 1000
  },
  "Supplier": {
    "supplies": [
      "MVIN",
      "MVME",
      "MVTA",
      "MVTB",
      "MVTK"
    ]
  },
  "Repairer": {
    "amount": 2,
    "targets": [
      "MVIN",
      "MVME",
      "MVTA",
      "MVTB",
      "MVTK"
    ]
  },
  "Factory": {
    "builds": [
      "MVIN",
      "MVME",
      "MVTA",
      "MVTB",
      "MVTK"
    ]
  }
}